azurisorting/__init__.py
azurisorting/azuricorrectivesorter.py
azurisorting/azurifastsorter.py
azurisorting/azurisorter.py
azurisorting-0.0.3.dist-info/METADATA
azurisorting-0.0.3.dist-info/WHEEL
azurisorting-0.0.3.dist-info/top_level.txt
azurisorting-0.0.3.dist-info/RECORD
