Metadata-Version: 2.1
Name: azurisorting
Version: 0.0.3
Summary: This sorter is used to sort datasets based on their ASCII Position.
Home-page: UNKNOWN
Author: Nathan Hornby
Author-email: alexmybestcat@gmail.com
License: UNKNOWN
Keywords: python,sorter,quick sorter,sort,fast sort,fast,corrective sorter,corrective,auto sorter,auto,easy sorter,easy
Platform: UNKNOWN
Classifier: Development Status :: 3 - Alpha
Classifier: Programming Language :: Python :: 3
Classifier: Operating System :: MacOS :: MacOS X
Classifier: Operating System :: Microsoft :: Windows
